super_scad_circle_sector/CircleSector.py
super_scad_circle_sector/__init__.py
super_scad_circle_sector-0.9.8.dist-info/LICENSE
super_scad_circle_sector-0.9.8.dist-info/METADATA
super_scad_circle_sector-0.9.8.dist-info/WHEEL
super_scad_circle_sector-0.9.8.dist-info/RECORD
